[
  {
    "table_name": "academic_years",
    "column_name": "id",
    "data_type": "integer",
    "is_nullable": "NO"
  },
  {
    "table_name": "academic_years",
    "column_name": "name",
    "data_type": "text",
    "is_nullable": "NO"
  },
  {
    "table_name": "academic_years",
    "column_name": "start_date",
    "data_type": "date",
    "is_nullable": "NO"
  },
  {
    "table_name": "academic_years",
    "column_name": "end_date",
    "data_type": "date",
    "is_nullable": "NO"
  },
  {
    "table_name": "academic_years",
    "column_name": "is_current",
    "data_type": "boolean",
    "is_nullable": "YES"
  },
  {
    "table_name": "announcements",
    "column_name": "id",
    "data_type": "integer",
    "is_nullable": "NO"
  },
  {
    "table_name": "announcements",
    "column_name": "title",
    "data_type": "text",
    "is_nullable": "NO"
  },
  {
    "table_name": "announcements",
    "column_name": "body",
    "data_type": "text",
    "is_nullable": "NO"
  },
  {
    "table_name": "announcements",
    "column_name": "target",
    "data_type": "text",
    "is_nullable": "YES"
  },
  {
    "table_name": "announcements",
    "column_name": "created_by",
    "data_type": "uuid",
    "is_nullable": "YES"
  },
  {
    "table_name": "announcements",
    "column_name": "created_at",
    "data_type": "timestamp with time zone",
    "is_nullable": "YES"
  },
  {
    "table_name": "assignment_submissions",
    "column_name": "id",
    "data_type": "integer",
    "is_nullable": "NO"
  },
  {
    "table_name": "assignment_submissions",
    "column_name": "assignment_id",
    "data_type": "integer",
    "is_nullable": "YES"
  },
  {
    "table_name": "assignment_submissions",
    "column_name": "student_id",
    "data_type": "integer",
    "is_nullable": "YES"
  },
  {
    "table_name": "assignment_submissions",
    "column_name": "submitted_at",
    "data_type": "timestamp with time zone",
    "is_nullable": "YES"
  },
  {
    "table_name": "assignment_submissions",
    "column_name": "file_url",
    "data_type": "text",
    "is_nullable": "YES"
  },
  {
    "table_name": "assignment_submissions",
    "column_name": "grade",
    "data_type": "text",
    "is_nullable": "YES"
  },
  {
    "table_name": "assignment_submissions",
    "column_name": "feedback",
    "data_type": "text",
    "is_nullable": "YES"
  },
  {
    "table_name": "assignments",
    "column_name": "id",
    "data_type": "integer",
    "is_nullable": "NO"
  },
  {
    "table_name": "assignments",
    "column_name": "title",
    "data_type": "text",
    "is_nullable": "NO"
  },
  {
    "table_name": "assignments",
    "column_name": "description",
    "data_type": "text",
    "is_nullable": "YES"
  },
  {
    "table_name": "assignments",
    "column_name": "subject_id",
    "data_type": "integer",
    "is_nullable": "YES"
  },
  {
    "table_name": "assignments",
    "column_name": "section_id",
    "data_type": "integer",
    "is_nullable": "YES"
  },
  {
    "table_name": "assignments",
    "column_name": "teacher_id",
    "data_type": "integer",
    "is_nullable": "YES"
  },
  {
    "table_name": "assignments",
    "column_name": "due_date",
    "data_type": "timestamp with time zone",
    "is_nullable": "YES"
  },
  {
    "table_name": "assignments",
    "column_name": "created_at",
    "data_type": "timestamp with time zone",
    "is_nullable": "YES"
  },
  {
    "table_name": "attendance",
    "column_name": "id",
    "data_type": "bigint",
    "is_nullable": "NO"
  },
  {
    "table_name": "attendance",
    "column_name": "student_id",
    "data_type": "bigint",
    "is_nullable": "NO"
  },
  {
    "table_name": "attendance",
    "column_name": "timetable_id",
    "data_type": "bigint",
    "is_nullable": "NO"
  },
  {
    "table_name": "attendance",
    "column_name": "date",
    "data_type": "date",
    "is_nullable": "NO"
  },
  {
    "table_name": "attendance",
    "column_name": "status",
    "data_type": "text",
    "is_nullable": "NO"
  },
  {
    "table_name": "attendance",
    "column_name": "remarks",
    "data_type": "text",
    "is_nullable": "YES"
  },
  {
    "table_name": "attendance",
    "column_name": "updated_at",
    "data_type": "timestamp with time zone",
    "is_nullable": "YES"
  },
  {
    "table_name": "classes",
    "column_name": "id",
    "data_type": "bigint",
    "is_nullable": "NO"
  },
  {
    "table_name": "classes",
    "column_name": "name",
    "data_type": "text",
    "is_nullable": "NO"
  },
  {
    "table_name": "classes",
    "column_name": "created_at",
    "data_type": "timestamp with time zone",
    "is_nullable": "YES"
  },
  {
    "table_name": "exams",
    "column_name": "id",
    "data_type": "integer",
    "is_nullable": "NO"
  },
  {
    "table_name": "exams",
    "column_name": "name",
    "data_type": "text",
    "is_nullable": "NO"
  },
  {
    "table_name": "exams",
    "column_name": "subject_id",
    "data_type": "integer",
    "is_nullable": "YES"
  },
  {
    "table_name": "exams",
    "column_name": "section_id",
    "data_type": "integer",
    "is_nullable": "YES"
  },
  {
    "table_name": "exams",
    "column_name": "academic_year_id",
    "data_type": "integer",
    "is_nullable": "YES"
  },
  {
    "table_name": "exams",
    "column_name": "exam_date",
    "data_type": "date",
    "is_nullable": "YES"
  },
  {
    "table_name": "exams",
    "column_name": "max_marks",
    "data_type": "integer",
    "is_nullable": "NO"
  },
  {
    "table_name": "exams",
    "column_name": "created_by",
    "data_type": "uuid",
    "is_nullable": "YES"
  },
  {
    "table_name": "fee_payments",
    "column_name": "id",
    "data_type": "integer",
    "is_nullable": "NO"
  },
  {
    "table_name": "fee_payments",
    "column_name": "student_id",
    "data_type": "integer",
    "is_nullable": "YES"
  },
  {
    "table_name": "fee_payments",
    "column_name": "fees_structure_id",
    "data_type": "integer",
    "is_nullable": "YES"
  },
  {
    "table_name": "fee_payments",
    "column_name": "amount_paid",
    "data_type": "numeric",
    "is_nullable": "NO"
  },
  {
    "table_name": "fee_payments",
    "column_name": "payment_status",
    "data_type": "text",
    "is_nullable": "YES"
  },
  {
    "table_name": "fee_payments",
    "column_name": "paid_at",
    "data_type": "timestamp with time zone",
    "is_nullable": "YES"
  },
  {
    "table_name": "fee_payments",
    "column_name": "collected_by",
    "data_type": "uuid",
    "is_nullable": "YES"
  },
  {
    "table_name": "fee_payments",
    "column_name": "remarks",
    "data_type": "text",
    "is_nullable": "YES"
  },
  {
    "table_name": "fee_payments",
    "column_name": "student_name",
    "data_type": "text",
    "is_nullable": "NO"
  },
  {
    "table_name": "fee_payments",
    "column_name": "roll_no",
    "data_type": "text",
    "is_nullable": "NO"
  },
  {
    "table_name": "fee_payments",
    "column_name": "fee_structure_id",
    "data_type": "bigint",
    "is_nullable": "YES"
  },
  {
    "table_name": "fee_payments",
    "column_name": "status",
    "data_type": "text",
    "is_nullable": "NO"
  },
  {
    "table_name": "fee_payments",
    "column_name": "payment_method",
    "data_type": "text",
    "is_nullable": "NO"
  },
  {
    "table_name": "fee_payments",
    "column_name": "updated_at",
    "data_type": "timestamp with time zone",
    "is_nullable": "NO"
  },
  {
    "table_name": "fees_structure",
    "column_name": "id",
    "data_type": "integer",
    "is_nullable": "NO"
  },
  {
    "table_name": "fees_structure",
    "column_name": "name",
    "data_type": "text",
    "is_nullable": "NO"
  },
  {
    "table_name": "fees_structure",
    "column_name": "amount",
    "data_type": "numeric",
    "is_nullable": "NO"
  },
  {
    "table_name": "fees_structure",
    "column_name": "academic_year_id",
    "data_type": "integer",
    "is_nullable": "YES"
  },
  {
    "table_name": "fees_structure",
    "column_name": "applicable_to",
    "data_type": "text",
    "is_nullable": "YES"
  },
  {
    "table_name": "fees_structure",
    "column_name": "due_date",
    "data_type": "date",
    "is_nullable": "YES"
  },
  {
    "table_name": "leave_requests",
    "column_name": "id",
    "data_type": "integer",
    "is_nullable": "NO"
  },
  {
    "table_name": "leave_requests",
    "column_name": "student_id",
    "data_type": "integer",
    "is_nullable": "YES"
  },
  {
    "table_name": "leave_requests",
    "column_name": "from_date",
    "data_type": "date",
    "is_nullable": "NO"
  },
  {
    "table_name": "leave_requests",
    "column_name": "to_date",
    "data_type": "date",
    "is_nullable": "NO"
  },
  {
    "table_name": "leave_requests",
    "column_name": "reason",
    "data_type": "text",
    "is_nullable": "YES"
  },
  {
    "table_name": "leave_requests",
    "column_name": "status",
    "data_type": "text",
    "is_nullable": "YES"
  },
  {
    "table_name": "leave_requests",
    "column_name": "reviewed_by",
    "data_type": "uuid",
    "is_nullable": "YES"
  },
  {
    "table_name": "leave_requests",
    "column_name": "reviewed_at",
    "data_type": "timestamp with time zone",
    "is_nullable": "YES"
  },
  {
    "table_name": "leave_requests",
    "column_name": "created_at",
    "data_type": "timestamp with time zone",
    "is_nullable": "YES"
  },
  {
    "table_name": "marks",
    "column_name": "id",
    "data_type": "integer",
    "is_nullable": "NO"
  },
  {
    "table_name": "marks",
    "column_name": "exam_id",
    "data_type": "integer",
    "is_nullable": "YES"
  },
  {
    "table_name": "marks",
    "column_name": "student_id",
    "data_type": "integer",
    "is_nullable": "YES"
  },
  {
    "table_name": "marks",
    "column_name": "marks_obtained",
    "data_type": "numeric",
    "is_nullable": "YES"
  },
  {
    "table_name": "marks",
    "column_name": "remarks",
    "data_type": "text",
    "is_nullable": "YES"
  },
  {
    "table_name": "marks",
    "column_name": "entered_by",
    "data_type": "integer",
    "is_nullable": "YES"
  },
  {
    "table_name": "marks",
    "column_name": "entered_at",
    "data_type": "timestamp with time zone",
    "is_nullable": "YES"
  },
  {
    "table_name": "materials",
    "column_name": "id",
    "data_type": "integer",
    "is_nullable": "NO"
  },
  {
    "table_name": "materials",
    "column_name": "title",
    "data_type": "text",
    "is_nullable": "NO"
  },
  {
    "table_name": "materials",
    "column_name": "description",
    "data_type": "text",
    "is_nullable": "YES"
  },
  {
    "table_name": "materials",
    "column_name": "file_url",
    "data_type": "text",
    "is_nullable": "YES"
  },
  {
    "table_name": "materials",
    "column_name": "subject_id",
    "data_type": "integer",
    "is_nullable": "YES"
  },
  {
    "table_name": "materials",
    "column_name": "section_id",
    "data_type": "integer",
    "is_nullable": "YES"
  },
  {
    "table_name": "materials",
    "column_name": "uploaded_by",
    "data_type": "integer",
    "is_nullable": "YES"
  },
  {
    "table_name": "materials",
    "column_name": "uploaded_at",
    "data_type": "timestamp with time zone",
    "is_nullable": "YES"
  },
  {
    "table_name": "message_thread_participants",
    "column_name": "thread_id",
    "data_type": "integer",
    "is_nullable": "NO"
  },
  {
    "table_name": "message_thread_participants",
    "column_name": "profile_id",
    "data_type": "uuid",
    "is_nullable": "NO"
  },
  {
    "table_name": "message_threads",
    "column_name": "id",
    "data_type": "integer",
    "is_nullable": "NO"
  },
  {
    "table_name": "message_threads",
    "column_name": "subject",
    "data_type": "text",
    "is_nullable": "YES"
  },
  {
    "table_name": "message_threads",
    "column_name": "created_at",
    "data_type": "timestamp with time zone",
    "is_nullable": "YES"
  },
  {
    "table_name": "messages",
    "column_name": "id",
    "data_type": "integer",
    "is_nullable": "NO"
  },
  {
    "table_name": "messages",
    "column_name": "thread_id",
    "data_type": "integer",
    "is_nullable": "YES"
  },
  {
    "table_name": "messages",
    "column_name": "sender_id",
    "data_type": "uuid",
    "is_nullable": "YES"
  },
  {
    "table_name": "messages",
    "column_name": "body",
    "data_type": "text",
    "is_nullable": "NO"
  },
  {
    "table_name": "messages",
    "column_name": "sent_at",
    "data_type": "timestamp with time zone",
    "is_nullable": "YES"
  },
  {
    "table_name": "profiles",
    "column_name": "id",
    "data_type": "uuid",
    "is_nullable": "NO"
  },
  {
    "table_name": "profiles",
    "column_name": "full_name",
    "data_type": "text",
    "is_nullable": "NO"
  }
]